LICENSE
MANIFEST.in
NOTICE
README.md
requirements.txt
setup.py
pystark/__init__.py
pystark/client.py
pystark/constants.py
pystark/env.py
pystark/logger.py
pystark/settings.py
pystark/database/__init__.py
pystark/database/mongo.py
pystark/database/sql.py
pystark/decorators/__init__.py
pystark/decorators/admins.py
pystark/decorators/callback.py
pystark/decorators/command.py
pystark/decorators/extras.py
pystark/decorators/inline.py
pystark/helpers/conversion.py
pystark/helpers/paste.py
pystark/helpers/process.py
pystark/helpers/pyrogress.py
pystark/helpers/requests.py
pystark/helpers/stickers.py
pystark/plugins/helpers.py
pystark/plugins/stark.py
pystark/plugins/addons/about.py
pystark/plugins/addons/bans.py
pystark/plugins/addons/broadcast.py
pystark/plugins/addons/buttons.py
pystark/plugins/addons/help.py
pystark/plugins/addons/id.py
pystark/plugins/addons/json.py
pystark/plugins/addons/start.py
pystark/plugins/addons/stats.py
pystark/plugins/addons/sudo.py
pystark/types/__init__.py
pystark/types/chat.py
pystark/types/dict.py
pystark/types/message.py
pystark/types/permissions.py
pystark/types/user.py
pystark/utils/__init__.py
pystark/utils/localization.py
pystark/utils/patch.py
some_random_name_for_testing.egg-info/PKG-INFO
some_random_name_for_testing.egg-info/SOURCES.txt
some_random_name_for_testing.egg-info/dependency_links.txt
some_random_name_for_testing.egg-info/not-zip-safe
some_random_name_for_testing.egg-info/requires.txt
some_random_name_for_testing.egg-info/top_level.txt