Metadata-Version: 2.1
Name: some-random-name-for-testing
Version: 0.0.0.0.2
Summary: An add-on extension to Pyrogram for absolute beginners
Home-page: https://github.com/StarkBotsIndustries/PyStark
Author: StarkProgrammer
Author-email: starkbotsindustries@gmail.com
License: GPLv3+
Project-URL: Support, https://t.me/StarkBotsChat
Project-URL: Community, https://t.me/StarkBots
Keywords: telegram,bot,pyrogram,python,telegram-bot
Platform: UNKNOWN
Classifier: Development Status :: 5 - Production/Stable
Classifier: Intended Audience :: Developers
Classifier: Intended Audience :: Education
Classifier: Intended Audience :: Information Technology
Classifier: License :: OSI Approved :: GNU General Public License v3 or later (GPLv3+)
Classifier: Operating System :: OS Independent
Classifier: Programming Language :: Python
Classifier: Programming Language :: Python :: 3
Classifier: Programming Language :: Python :: 3.10
Classifier: Programming Language :: Python :: 3.11
Classifier: Natural Language :: English
Classifier: Topic :: Communications :: Chat
Classifier: Topic :: Education :: Testing
Classifier: Topic :: Software Development :: Libraries
Classifier: Topic :: Software Development :: Libraries :: Python Modules
Requires-Python: >=3.10
License-File: LICENSE
License-File: NOTICE
